models/__init__.py
models/common.py
models/experimental.py
models/export.py
models/yolo.py
utils/__init__.py
utils/activations.py
utils/datasets.py
utils/general.py
utils/google_utils.py
utils/torch_utils.py
yolov5processor/__init__.py
yolov5processor/infer.py
yolov5processor/models/__init__.py
yolov5processor/models/common.py
yolov5processor/models/experimental.py
yolov5processor/models/export.py
yolov5processor/models/yolo.py
yolov5processor/utils/__init__.py
yolov5processor/utils/activations.py
yolov5processor/utils/datasets.py
yolov5processor/utils/general.py
yolov5processor/utils/google_utils.py
yolov5processor/utils/torch_utils.py
yolov5processor-1.2.dist-info/LICENSE
yolov5processor-1.2.dist-info/METADATA
yolov5processor-1.2.dist-info/WHEEL
yolov5processor-1.2.dist-info/top_level.txt
yolov5processor-1.2.dist-info/RECORD
